ghast/__init__.py
ghast/__main__.py
ghast/server.py
ghast-0.1.0.dist-info/LICENSE
ghast-0.1.0.dist-info/METADATA
ghast-0.1.0.dist-info/WHEEL
ghast-0.1.0.dist-info/entry_points.txt
ghast-0.1.0.dist-info/top_level.txt
ghast-0.1.0.dist-info/RECORD
